{
  "title": "The Smallest at NCN 2025",
  "author": "Raphaël Labro",
  "description": "In July 2025, I had the chance to present the Smallest at the Nuits du Causse Noir 2025, at Les Pradines campsite. NCN is the annual astronomy gathering not to be missed: a special moment between the community and the nights, with breathtaking sky quality.",
  "webLink": "https://la3emedim.fr",
  "latitude": 44.134568,
  "longitude": 3.357813,
  "mainPhoto": "https://la3emedim.fr/assets/Ncn2025_5.jpeg",
  "additionalPhotos": [
    "https://la3emedim.fr/assets/Ncn2025_1.JPG",
    "https://la3emedim.fr/assets/Ncn2025_2.JPG",
    "https://la3emedim.fr/assets/Ncn2025_3.JPG",
    "https://la3emedim.fr/assets/Ncn2025_4.jpeg",
    "https://la3emedim.fr/assets/Ncn2025_5.JPG",
    "https://la3emedim.fr/assets/Ncn2025_6.jpeg",
    "https://la3emedim.fr/assets/Ncn2025_7.jpeg"
  ],
  "draft": false
}
